ascim/__init__.py
ascim/__test__.py
ascim/ascim.py
ascim/draw.py
ascim/table.py
ascim/utils.py
ascim-0.1.1.dist-info/LICENSE
ascim-0.1.1.dist-info/METADATA
ascim-0.1.1.dist-info/WHEEL
ascim-0.1.1.dist-info/top_level.txt
ascim-0.1.1.dist-info/RECORD
