Metadata-Version: 2.1
Name: ascim
Version: 0.1.1
Summary: Manipulate ASCII Art & Tables in a bitmap-image-like manner.
Home-page: https://github.com/fakefred/ascim
Author: fakefred
Author-email: fakefred@protonmail.ch
License: MIT
Project-URL: LiberaPay, https://liberapay.com/fakefred/donate
Keywords: ascii art
Platform: UNKNOWN
Classifier: Development Status :: 3 - Alpha
Classifier: License :: OSI Approved :: MIT License
Requires-Python: >=3.5
